{"cameraMode":{"drawMode":0,"name":"Shaded","section":"Shading Mode"},"sceneLighting":false,"audioPlay":false,"sceneViewState":{"showFog":true,"showMaterialUpdate":false,"showSkybox":false,"showFlares":true,"showImageEffects":true,"showParticleSystems":true},"in2DMode":false,"pivot":{"x":0.024097740650177003,"y":0.020757436752319337,"z":-0.004834357649087906},"rotation":{"x":0.12502877414226533,"y":0.2334386557340622,"z":-0.030275970697402955,"w":0.9638291001319885},"size":1.4170005321502686,"orthographic":false}